LICENSE.txt
MANIFEST.in
README.rst
setup.py
django_register_activate.egg-info/PKG-INFO
django_register_activate.egg-info/SOURCES.txt
django_register_activate.egg-info/dependency_links.txt
django_register_activate.egg-info/top_level.txt
docs/Example settings.py
register_activate/__init__.py
register_activate/admin.py
register_activate/apps.py
register_activate/email_auth.py
register_activate/forms.py
register_activate/models.py
register_activate/tests.py
register_activate/urls.py
register_activate/views.py
register_activate/templates/register_activate/ErrorPage.html
register_activate/templates/register_activate/activation.html
register_activate/templates/register_activate/base.html
register_activate/templates/register_activate/log_out.html
register_activate/templates/register_activate/mainpage.html
register_activate/templates/register_activate/sign_in.html
register_activate/templates/register_activate/sign_up.html
register_activate/templates/register_activate/thankyou.html